hor2vec/__init__.py
hor2vec/__main__.py
hor2vec-2.2.1.dist-info/entry_points.txt
hor2vec-2.2.1.dist-info/LICENSE
hor2vec-2.2.1.dist-info/WHEEL
hor2vec-2.2.1.dist-info/METADATA
hor2vec-2.2.1.dist-info/RECORD
