Metadata-Version: 2.1
Name: hor2vec
Version: 2.2.1
Summary: Change your horizontal pure text to vertical with some options.
Home-page: https://github.com/M157q/hor2vec
License: UNKNOWN
Author: Frank Jheng
Author-email: m157q.tw@gmail.com
Classifier: License :: OSI Approved :: GNU General Public License v3 or later (GPLv3+)
